semantic_text_similarity/__init__.py
semantic_text_similarity/data/__init__.py
semantic_text_similarity/data/data.py
semantic_text_similarity/data/test_data.py
semantic_text_similarity/data/sts_b/__init__.py
semantic_text_similarity/data/sts_b/sts-dev.csv
semantic_text_similarity/data/sts_b/sts-test.csv
semantic_text_similarity/data/sts_b/sts-train.csv
semantic_text_similarity/models/__init__.py
semantic_text_similarity/models/test_util.py
semantic_text_similarity/models/util.py
semantic_text_similarity/models/bert/__init__.py
semantic_text_similarity/models/bert/bert_preprocessing.py
semantic_text_similarity/models/bert/clinical_similarity.py
semantic_text_similarity/models/bert/similarity.py
semantic_text_similarity/models/bert/web_similarity.py
semantic_text_similarity/models/string_similarity/__init__.py
semantic_text_similarity/models/string_similarity/lexical_similarity_metrics.py
semantic_text_similarity-1.0.3.dist-info/LICENSE
semantic_text_similarity-1.0.3.dist-info/METADATA
semantic_text_similarity-1.0.3.dist-info/WHEEL
semantic_text_similarity-1.0.3.dist-info/top_level.txt
semantic_text_similarity-1.0.3.dist-info/RECORD
