Metadata-Version: 2.1
Name: semantic-text-similarity
Version: 1.0.3
Summary: implementations of models and metrics for semantic text similarity. that's it.
Home-page: https://github.com/AndriyMulyar/semantic-text-similarity
Author: Andriy Mulyar, Elliot Schumacher and Mark Dredze
Author-email: contact@andriymulyar.com
License: MIT
Platform: UNKNOWN
Classifier: Development Status :: 4 - Beta
Classifier: License :: OSI Approved :: MIT License
Classifier: Programming Language :: Python :: 3.5
Classifier: Natural Language :: English
Classifier: Topic :: Text Processing :: Linguistic
Classifier: Intended Audience :: Science/Research
Requires-Dist: torch
Requires-Dist: strsim
Requires-Dist: fuzzywuzzy[speedup]
Requires-Dist: pytorch-transformers (==1.1.0)
Requires-Dist: scipy
